LICENSE
shared_memory_dict/__init__.py
shared_memory_dict/caches/__init__.py
shared_memory_dict/caches/aiocache.py
shared_memory_dict/caches/django.py
shared_memory_dict/dict.py
shared_memory_dict/hooks.py
shared_memory_dict/lock.py
shared_memory_dict/serializers.py
shared_memory_dict/templates.py
shared_memory_dict-0.7.1.dist-info/LICENSE
shared_memory_dict-0.7.1.dist-info/WHEEL
shared_memory_dict-0.7.1.dist-info/METADATA
shared_memory_dict-0.7.1.dist-info/RECORD
