Metadata-Version: 2.1
Name: shared-memory-dict
Version: 0.7.1
Summary: A very simple shared memory dict implementation
Home-page: https://github.com/luizalabs/shared-memory-dict
License: MIT
Keywords: django,aiocache,shared memory
Author: Arquitetura LuizaLabs
Author-email: arquitetura@luizalabs.com
Requires-Python: >=3.8,<4.0
Classifier: License :: OSI Approved :: MIT License
Classifier: Operating System :: OS Independent
Classifier: Programming Language :: Python :: 3
Classifier: Programming Language :: Python :: 3.8
Classifier: Programming Language :: Python :: 3.9
Classifier: Topic :: Software Development :: Libraries :: Python Modules
Provides-Extra: aiocache
Provides-Extra: all
Provides-Extra: django
Requires-Dist: aiocache (>=0.11.1,<0.12.0); extra == "aiocache" or extra == "all"
Requires-Dist: django (>=3.0.8,<4.0.0); extra == "django" or extra == "all"
Project-URL: Repository, https://github.com/luizalabs/shared-memory-dict
